epr2md/__init__.py
epr2md/_version.py
epr2md/epr2md.py
epr2md/resources/__init__.py
epr2md/resources/loggingConfiguration.json
epr2md-0.2.1.dist-info/LICENSE
epr2md-0.2.1.dist-info/METADATA
epr2md-0.2.1.dist-info/WHEEL
epr2md-0.2.1.dist-info/entry_points.txt
epr2md-0.2.1.dist-info/top_level.txt
epr2md-0.2.1.dist-info/RECORD
