Metadata-Version: 2.1
Name: epr2md
Version: 0.2.1
Summary: Converts EPR files to Markdown
Author-email: "Humberto A. Sanchez II" <Humbert.A.Sanchez.II@gmail.com>
Maintainer-email: "Humberto A. Sanchez II" <Humbert.A.Sanchez.II@gmail.com>
License: GNU AFFERO GENERAL PUBLIC LICENSE
Project-URL: Repository, https://github.com/hasii2011/epr2md
Keywords: epr,issues,python
License-File: LICENSE
Requires-Dist: click~=8.1.7
